Metadata-Version: 2.1
Name: pytwinkle
Version: 0.1.1
Summary: Twinkle sip client, ported to a python module.
Home-page: https://github.com/RoberWare/pytwinkle
Author: Roberto Lama Rodriguez
Author-email: roberlama@gmail.com
License: MIT
Keywords: sip,softphone,python,module,iot,rpi,raspberry
Platform: UNKNOWN
Classifier: Development Status :: 3 - Alpha
Classifier: Intended Audience :: Developers
Classifier: Topic :: Software Development :: Build Tools
Classifier: License :: OSI Approved :: MIT License
Classifier: Programming Language :: Python :: 3
Classifier: Programming Language :: Python :: 3.4
Classifier: Programming Language :: Python :: 3.5
Classifier: Programming Language :: Python :: 3.6
